{
    "title": "Phone",
    "description": "Dynamic form generator is a form of the things in the line",
    "name": "",
    "version": "1.0.0",
    "elements": [
        {
            "id": "item-af251d12-b924-4f06-95ba-c74d743fe111",
            "name": "Simple Table",
            "type": "advtable",
            "isRow": false,
            "label": "Advance Table",
            "contents": [
                [
                    {
                        "id": "item-104b8659-d888-43a2-90e9-5f8129e1ffa8",
                        "name": "Multi-Select Dropdown",
                        "type": "multipleselect",
                        "label": "Multi select dropdown",
                        "answer": "",
                        "isRequired": false,
                        "actionMessage": "",
                        "initialAnswer": "",
                        "isConditional": false,
                        "fromManualList": false,
                        "islinked_query": "project"
                    }, {
                        "type": "dropdown",
                        "id": "select1",
                        "label": "Select from below drop down testelect from below drop down testelect from below drop down testelect from below drop down testelect from below drop down test",
                        "isRequired": true,
                        "requiredErrorText": "Drop down is required",
                        "commentPlaceholder": "comment are place",
                        "fromManualList": false,
                        "islinked": true,
                        "choice": [
                            {
                                "value": "item1",
                                "text": "This is item 1."
                            },
                            {
                                "value": "item2",
                                "text": "This is item 2."
                            },
                            {
                                "value": "item3",
                                "text": "This is item 3."
                            },
                            {
                                "value": "item4",
                                "text": "This is item 4."
                            },
                            {
                                "value": "item5",
                                "text": "This is item 5."
                            }
                        ],
                        "showOtherItem": true,
                        "showNoneItem": true,
                        "otherErrorText": "Empty comment required",
                        "placeholder": "Select...OKkk"
                    }
                ],
                [
                    {
                        "id": "item-104b8659-d888-43a2-90e9-5f8129e1ffa4",
                        "name": "Multi-Select Dropdown",
                        "type": "multipleselect",
                        "label": "Multi select dropdown",
                        "answer": "",
                        "isRequired": false,
                        "actionMessage": "",
                        "initialAnswer": "",
                        "isConditional": false,
                        "fromManualList": false,
                        "islinked_query": "project"
                    }, {
                        "type": "dropdown",
                        "id": "select12",
                        "label": "Select from below drop down testelect from below drop down testelect from below drop down testelect from below drop down testelect from below drop down test",
                        "isRequired": true,
                        "requiredErrorText": "Drop down is required",
                        "commentPlaceholder": "comment are place",
                        "fromManualList": false,
                        "islinked": true,
                        "choice": [
                            {
                                "value": "item1",
                                "text": "This is item 1."
                            },
                            {
                                "value": "item2",
                                "text": "This is item 2."
                            },
                            {
                                "value": "item3",
                                "text": "This is item 3."
                            },
                            {
                                "value": "item4",
                                "text": "This is item 4."
                            },
                            {
                                "value": "item5",
                                "text": "This is item 5."
                            }
                        ],
                        "showOtherItem": true,
                        "showNoneItem": true,
                        "otherErrorText": "Empty comment required",
                        "placeholder": "Select...OKkk"
                    }
                ]
               
            ],
            "isRequired": false,
            "selectedLinkListLabel": ""
        }
    ]
}
